nicechat/test_llm.py
nicechat/__init__.py
nicechat/llm.py
nicechat/app.py
nicechat/markdown_ext.py
nicechat-0.1.1.dist-info/WHEEL
nicechat-0.1.1.dist-info/entry_points.txt
nicechat-0.1.1.dist-info/METADATA
nicechat-0.1.1.dist-info/RECORD
