Metadata-Version: 2.3
Name: nicechat
Version: 0.1.1
Summary: An llm chat gui
Author: HuangYi
Author-email: HuangYi <yi.codeplayer@gmail.com>
Requires-Dist: nicegui>=1.4.21
Requires-Dist: openai>=1.12.0
Requires-Dist: anthropic>=0.25.0
Requires-Dist: latex2mathml>=3.74.0
Requires-Dist: markdown2>=2.4.10
Requires-Dist: pywebview>=5.4
Requires-Python: >=3.8
